haanna/__init__.py
haanna/haanna.py
haanna-0.13.5.dist-info/LICENSE
haanna-0.13.5.dist-info/METADATA
haanna-0.13.5.dist-info/WHEEL
haanna-0.13.5.dist-info/top_level.txt
haanna-0.13.5.dist-info/RECORD
