Metadata-Version: 2.1
Name: haanna
Version: 0.13.5
Summary: Plugwise Anna API to use in conjunction with Home Assistant.
Home-page: https://github.com/laetificat/haanna
Author: Laetificat
Author-email: k.heruer@gmail.com
License: MIT
Keywords: HomeAssistant HA Home Assistant Anna Plugwise
Platform: UNKNOWN
Requires-Dist: requests
Requires-Dist: datetime
Requires-Dist: pytz
